randize/__init__.py
randize/randize.py
randize-1.3.dist-info/LICENSE
randize-1.3.dist-info/METADATA
randize-1.3.dist-info/WHEEL
randize-1.3.dist-info/top_level.txt
randize-1.3.dist-info/RECORD
