Metadata-Version: 2.1
Name: randize
Version: 1.3
Summary: Ultimate Python Randomizer Library
Home-page: https://github.com/BlazeDevelop/randize
Author: Vladimir
Author-email: funquenop@gmail.com
Classifier: Programming Language :: Python :: 3
Classifier: License :: OSI Approved :: MIT License
Classifier: Operating System :: OS Independent
Requires-Python: >=3.8
License-File: LICENSE
Requires-Dist: requests
Requires-Dist: pytz
Requires-Dist: uuid
Requires-Dist: datetime
Requires-Dist: lorem
Requires-Dist: deep-translator
